[
    {
        "username":"mattystiles",
        "nickname":"Matt Stiles",
        "uniqueId":"mattystiles",
        "verified":false,
        "region":"US",
        "followerCount":1003,
        "followingCount":736,
        "heartCount":130600,
        "videoCount":99,
        "diggCount":0
    },
    {
        "username":"evablytheofficial",
        "nickname":"eva blythe",
        "uniqueId":"evablytheofficial",
        "verified":false,
        "region":"US",
        "followerCount":2527,
        "followingCount":562,
        "heartCount":11300,
        "videoCount":72,
        "diggCount":0
    }
]