[
    {
        "username":"mattystiles",
        "nickname":"Matt Stiles",
        "uniqueId":"mattystiles",
        "verified":false,
        "region":"US",
        "followerCount":824,
        "followingCount":669,
        "heartCount":100900,
        "videoCount":90,
        "diggCount":0
    },
    {
        "username":"evablytheofficial",
        "nickname":"eva \ud83c\udf1f",
        "uniqueId":"evablytheofficial",
        "verified":false,
        "region":"US",
        "followerCount":206,
        "followingCount":126,
        "heartCount":558,
        "videoCount":10,
        "diggCount":0
    }
]