[
    {
        "username":"mattystiles",
        "nickname":"Matt Stiles",
        "uniqueId":"mattystiles",
        "verified":false,
        "region":"US",
        "followerCount":1006,
        "followingCount":717,
        "heartCount":128300,
        "videoCount":98,
        "diggCount":0
    },
    {
        "username":"evablytheofficial",
        "nickname":"eva blythe",
        "uniqueId":"evablytheofficial",
        "verified":false,
        "region":"US",
        "followerCount":2133,
        "followingCount":460,
        "heartCount":7233,
        "videoCount":38,
        "diggCount":0
    }
]