[
    {
        "id":58362,
        "rank":1,
        "affected":42,
        "status":"Assigned",
        "est_fixed":"11\/06\/2024 20:00",
        "name":"Silver Lake",
        "longitude":-118.26059,
        "latitude":34.089488,
        "fetched":1730947203092
    },
    {
        "id":58363,
        "rank":1,
        "affected":291,
        "status":"Crews Working",
        "est_fixed":"11\/06\/2024 17:00",
        "name":"Tujunga",
        "longitude":-118.273322,
        "latitude":34.240714,
        "fetched":1730947203092
    },
    {
        "id":58364,
        "rank":1,
        "affected":1114,
        "status":"Crews Working",
        "est_fixed":null,
        "name":"Van Nuys",
        "longitude":-118.484114,
        "latitude":34.19353,
        "fetched":1730947203092
    },
    {
        "id":58365,
        "rank":1,
        "affected":647,
        "status":"Crews Working",
        "est_fixed":"11\/06\/2024 19:00",
        "name":"Sunland",
        "longitude":-118.321167,
        "latitude":34.259408,
        "fetched":1730947203092
    },
    {
        "id":58366,
        "rank":1,
        "affected":7,
        "status":"Assigned",
        "est_fixed":"11\/06\/2024 21:00",
        "name":"West Hills",
        "longitude":-118.620065,
        "latitude":34.213596,
        "fetched":1730947203092
    },
    {
        "id":58367,
        "rank":1,
        "affected":250,
        "status":"Crews Working",
        "est_fixed":"11\/07\/2024 01:00",
        "name":"Tarzana",
        "longitude":-118.535861,
        "latitude":34.178168,
        "fetched":1730947203092
    },
    {
        "id":58368,
        "rank":1,
        "affected":43,
        "status":"Crews Working",
        "est_fixed":"11\/06\/2024 15:00",
        "name":"Pacoima",
        "longitude":-118.406194,
        "latitude":34.273956,
        "fetched":1730947203092
    },
    {
        "id":58369,
        "rank":1,
        "affected":240,
        "status":"Assigned",
        "est_fixed":"11\/06\/2024 19:00",
        "name":"Encino",
        "longitude":-118.474228,
        "latitude":34.154582,
        "fetched":1730947203092
    },
    {
        "id":58370,
        "rank":3,
        "affected":13,
        "status":"Assigned",
        "est_fixed":null,
        "name":"Chatsworth",
        "longitude":-118.603895,
        "latitude":34.257511,
        "fetched":1730947203092
    },
    {
        "id":58371,
        "rank":2,
        "affected":378,
        "status":"Assigned",
        "est_fixed":"11\/06\/2024 11:30",
        "name":"Sylmar",
        "longitude":-118.440184,
        "latitude":34.3101,
        "fetched":1730947203092
    },
    {
        "id":58372,
        "rank":1,
        "affected":649,
        "status":"Crews Working",
        "est_fixed":"11\/06\/2024 19:00",
        "name":"Sylmar",
        "longitude":-118.412869,
        "latitude":34.32288,
        "fetched":1730947203092
    },
    {
        "id":58373,
        "rank":3,
        "affected":305,
        "status":"Assigned",
        "est_fixed":"11\/06\/2024 19:00",
        "name":"Sylmar",
        "longitude":-118.403483,
        "latitude":34.316217,
        "fetched":1730947203092
    },
    {
        "id":58374,
        "rank":2,
        "affected":34,
        "status":"Assigned",
        "est_fixed":"11\/06\/2024 17:00",
        "name":"Pacoima",
        "longitude":-118.431661,
        "latitude":34.259212,
        "fetched":1730947203092
    },
    {
        "id":58375,
        "rank":1,
        "affected":8,
        "status":"Assigned",
        "est_fixed":null,
        "name":"Woodland Hills",
        "longitude":-118.62064,
        "latitude":34.16219,
        "fetched":1730947203092
    },
    {
        "id":58376,
        "rank":2,
        "affected":20,
        "status":"Crews Working",
        "est_fixed":"11\/06\/2024 21:00",
        "name":"Chatsworth",
        "longitude":-118.572097,
        "latitude":34.244974,
        "fetched":1730947203092
    },
    {
        "id":58377,
        "rank":1,
        "affected":586,
        "status":"Crews Working",
        "est_fixed":"11\/06\/2024 19:00",
        "name":"Chatsworth",
        "longitude":-118.579291,
        "latitude":34.250546,
        "fetched":1730947203092
    },
    {
        "id":58378,
        "rank":1,
        "affected":0,
        "status":"Assigned",
        "est_fixed":null,
        "name":"Northridge",
        "longitude":-118.558774,
        "latitude":34.238263,
        "fetched":1730947203092
    },
    {
        "id":58379,
        "rank":1,
        "affected":3,
        "status":"Crews Working",
        "est_fixed":null,
        "name":"Mission Hills",
        "longitude":-118.450372,
        "latitude":34.307835,
        "fetched":1730947203092
    }
]