[
    {
        "id":59971,
        "name":"Del Rey",
        "rank":1,
        "affected":27,
        "status":"Assigned",
        "est_fixed":"11\/23\/2024 19:30",
        "longitude":-118.422616,
        "latitude":33.987907,
        "fetched":1732410584382
    },
    {
        "id":59972,
        "name":"El Segundo",
        "rank":1,
        "affected":16,
        "status":"Crews Working",
        "est_fixed":"11\/23\/2024 09:00",
        "longitude":-118.428257,
        "latitude":33.930653,
        "fetched":1732410584382
    }
]