[
    {
        "id":58780,
        "name":"Shadow Hills",
        "rank":1,
        "affected":349,
        "status":"Crews Working",
        "est_fixed":"11\/06\/2024 19:00",
        "longitude":-118.349998,
        "latitude":34.259043,
        "fetched":1730995458359
    },
    {
        "id":58781,
        "name":"Northridge",
        "rank":1,
        "affected":0,
        "status":"Reported Outage",
        "est_fixed":null,
        "longitude":-118.558774,
        "latitude":34.238263,
        "fetched":1730995458359
    }
]